{
    "playlist_name": "Live Sports Events",
    "owner": "Md Sohanur Rahman Hady",
    "telegram": "https://t.me/livesportsplay",
    "last_updated": "2026-03-27 04:30:30 AM (BD Time)",
    "total_links": 6,
    "matches": [
        {
            "Category": "Cricket",
            "Tour/Group name": "PSL T20",
            "match name": "Pakistan Super League",
            "Start time": "March 26, 2026, at 1:30 PM UTC",
            "End time": "May 7, 2026, at 8 PM UTC",
            "Status": "LIVE",
            "referer": "https://player0003.com/",
            "User agent": "Mozilla/5.0 (Windows NT 10.0; Win64; x64) AppleWebKit/537.36 (KHTML, like Gecko) Chrome/120.0.0.0 Safari/537.36",
            "Channels": [
                {
                    "Channel name": "PTV Sports",
                    "Language": "English",
                    "Embed link": "https://dadocric.st/player.php?id=ptvsp",
                    "Stream link": "https://dz2.bhalocast.com:7059/hls/ptvscpr.m3u8?md5=sycQK6odNgQpo9KFqVBidQ&expires=1774569017&ch=ptvscpr&s=bae56d9b47e4ec29c8f48e014918ca8f"
                },
                {
                    "Channel name": "A Sports HD",
                    "Language": "English",
                    "Embed link": "https://dadocric.st/player.php?id=asports",
                    "Stream link": "https://dz2.bhalocast.com:7059/hls/asportsd.m3u8?md5=-fcHI0C49EhzIQ81u-Jjbg&expires=1774569018&ch=asportsd&s=b638e02613de9973b04985683ce91ba8"
                },
                {
                    "Channel name": "Ten Sports",
                    "Language": "English",
                    "Embed link": "https://dadocric.st/player.php?id=tensp",
                    "Stream link": "https://dz2.bhalocast.com:7059/hls/tensp.m3u8?md5=B-ld0jQAEeuc8mfwTNKoIA&expires=1774569019&ch=tensp&s=18069680eccc9b22750f64fb42ba78d3"
                },
                {
                    "Channel name": "Geo Super",
                    "Language": "English",
                    "Embed link": "https://dadocric.st/player.php?id=geosuper",
                    "Stream link": "https://dz2.bhalocast.com:7059/hls/geosp.m3u8?md5=oLa6Kr3Jy-sjKFQeXOOsiA&expires=1774569021&ch=geosp&s=ce9c6df653489f615fc9e0d1bd5813a4"
                }
            ]
        },
        {
            "Category": "Cricket",
            "Tour/Group name": "T20 League",
            "match name": "Legends League Cricket",
            "Start time": "March 16, 2026, at 1:30 PM UTC",
            "End time": "March 27, 2026, at 7 PM UTC",
            "Status": "LIVE",
            "referer": "https://player0003.com/",
            "User agent": "Mozilla/5.0 (Windows NT 10.0; Win64; x64) AppleWebKit/537.36 (KHTML, like Gecko) Chrome/120.0.0.0 Safari/537.36",
            "Channels": [
                {
                    "Channel name": "Sony Sports Ten 1",
                    "Language": "English",
                    "Embed link": "https://dadocric.st/player.php?id=ten1",
                    "Stream link": "https://dz2.bhalocast.com:7059/hls/ten1co.m3u8?md5=yfqmogk9m-rQuRUjiYNf7A&expires=1774569023&ch=ten1co&s=05a30ec0cb5c661254bab4b706fc5fa9"
                },
                {
                    "Channel name": "Sony Sports Ten 3",
                    "Language": "Hindi",
                    "Embed link": "https://dadocric.st/player.php?id=ten3",
                    "Stream link": "https://dz2.bhalocast.com:7059/hls/ten3sd.m3u8?md5=wwxgs0fRbCtmUQcRQhbTog&expires=1774569025&ch=ten3sd&s=8c336cc42c211505810ddecd4bf17885"
                }
            ]
        }
    ]
}