{
    "playlist_name": "Live Sports Events",
    "owner": "Md Sohanur Rahman Hady",
    "telegram": "https://t.me/livesportsplay",
    "last_updated": "2026-03-28 04:01:04 PM (BD Time)",
    "total_links": 24,
    "matches": [
        {
            "Category": "Cricket",
            "Tour/Group name": "PSL T20",
            "match name": "Pakistan Super League",
            "Start time": "March 26, 2026, at 1:30 PM UTC",
            "End time": "May 7, 2026, at 8 PM UTC",
            "Status": "LIVE",
            "referer": "https://player0003.com/",
            "User agent": "Mozilla/5.0 (Windows NT 10.0; Win64; x64) AppleWebKit/537.36 (KHTML, like Gecko) Chrome/120.0.0.0 Safari/537.36",
            "Channels": [
                {
                    "Channel name": "PTV Sports",
                    "Language": "English",
                    "Embed link": "https://dadocric.st/player.php?id=ptvsp",
                    "Stream link": "https://dz2.bhalocast.com:7059/hls/ptvscpr.m3u8?md5=cMxN92eNE7RRXkTItjSaHA&expires=1774696821&ch=ptvscpr&s=0a4ecd717db0d39ac74687f00472b5b5"
                },
                {
                    "Channel name": "A Sports HD",
                    "Language": "English",
                    "Embed link": "https://dadocric.st/player.php?id=asports",
                    "Stream link": "https://dz2.bhalocast.com:7059/hls/asportsd.m3u8?md5=9AxM567aUus3FgbgpZCznQ&expires=1774696823&ch=asportsd&s=618d26a9657922563cad4269c46eeebb"
                },
                {
                    "Channel name": "Ten Sports",
                    "Language": "English",
                    "Embed link": "https://dadocric.st/player.php?id=tensp",
                    "Stream link": "https://dz2.bhalocast.com:7059/hls/tensp.m3u8?md5=JFWwVG4yNjHQxvVWQAKAig&expires=1774696825&ch=tensp&s=b083aa6f7576eae7e486a9a083b7cea9"
                },
                {
                    "Channel name": "Geo Super",
                    "Language": "English",
                    "Embed link": "https://dadocric.st/player.php?id=geosuper",
                    "Stream link": "https://dz2.bhalocast.com:7059/hls/geosp.m3u8?md5=0yvOmc-P6GnkjrOCWD9bUQ&expires=1774696826&ch=geosp&s=bdb4f62c3fe2c9a1ae6375d6b039300f"
                }
            ]
        },
        {
            "Category": "Cricket",
            "Tour/Group name": "IPL T20",
            "match name": "IPL 2026",
            "Start time": "March 28, 2026, at 1:30 PM UTC",
            "End time": "June 3, 2026, at 8 PM UTC",
            "Status": "UPCOMING",
            "referer": "https://player0003.com/",
            "User agent": "Mozilla/5.0 (Windows NT 10.0; Win64; x64) AppleWebKit/537.36 (KHTML, like Gecko) Chrome/120.0.0.0 Safari/537.36",
            "Channels": [
                {
                    "Channel name": "Willow Cricket",
                    "Language": "English",
                    "Embed link": "https://dadocric.st/player.php?id=willow",
                    "Stream link": "https://dz2.bhalocast.com:7059/hls/dxdwillo.m3u8?md5=HMo8gA28fQUFCquKw2y-Fg&expires=1774696829&ch=dxdwillo&s=07ea33064e578e216ca703ed242d8b17"
                },
                {
                    "Channel name": "Willow Xtra",
                    "Language": "HIndi",
                    "Embed link": "https://dadocric.st/player.php?id=willowextra",
                    "Stream link": "https://dz2.bhalocast.com:7059/hls/dxwillo2.m3u8?md5=P--4ulQz72SMEEPoj8U-Rw&expires=1774696831&ch=dxwillo2&s=bca9f762700ab1c86960dda4dd27f633"
                },
                {
                    "Channel name": "Star Sports 1",
                    "Language": "English",
                    "Embed link": "https://dadocric.st/player.php?id=starsp",
                    "Stream link": "https://dz2.bhalocast.com:7059/hls/str1crows.m3u8?md5=vysAL1HcZcTMqoqB6FI5FA&expires=1774696832&ch=str1crows&s=7dc796e22b18c968d5daccefe0cf0c5e"
                },
                {
                    "Channel name": "Star Sports 2",
                    "Language": "English",
                    "Embed link": "https://dadocric.st/player.php?id=starsp2",
                    "Stream link": "https://dz2.bhalocast.com:7059/hls/str2cows.m3u8?md5=gWhEC_5e5xoHsa9MwCXDjQ&expires=1774696834&ch=str2cows&s=5424558eaab2b9fa0f20fb57eccf6a5f"
                },
                {
                    "Channel name": "Star Sports Hindi",
                    "Language": "Hindi",
                    "Embed link": "https://dadocric.st/player.php?id=starsp3",
                    "Stream link": "https://dz2.bhalocast.com:7059/hls/str1crowshi.m3u8?md5=XSm_2VlDf4epUA4y3JGLxA&expires=1774696835&ch=str1crowshi&s=803801f1d5f8f238933a2987196dc86b"
                }
            ]
        },
        {
            "Category": "Cricket",
            "Tour/Group name": "IPL T20",
            "match name": "RCB vs SRH",
            "Start time": "March 28, 2026, at 2 PM UTC",
            "End time": "March 28, 2026, at 6 PM UTC",
            "Status": "UPCOMING",
            "referer": "https://player0003.com/",
            "User agent": "Mozilla/5.0 (Windows NT 10.0; Win64; x64) AppleWebKit/537.36 (KHTML, like Gecko) Chrome/120.0.0.0 Safari/537.36",
            "Channels": [
                {
                    "Channel name": "Willow Cricket",
                    "Language": "English",
                    "Embed link": "https://dadocric.st/player.php?id=willow",
                    "Stream link": "https://dz2.bhalocast.com:7059/hls/dxdwillo.m3u8?md5=1xqTyJvNozGZ21ZMj2OoqQ&expires=1774696840&ch=dxdwillo&s=0bf81230bf9d3c55770985ef68d64b77"
                },
                {
                    "Channel name": "Willow Xtra",
                    "Language": "HIndi",
                    "Embed link": "https://dadocric.st/player.php?id=willowextra",
                    "Stream link": "https://dz2.bhalocast.com:7059/hls/dxwillo2.m3u8?md5=GBxPPBMGS1KIW8s7B5OLLQ&expires=1774696842&ch=dxwillo2&s=8deecf2bae9abad6ea32ed4868c3c4cd"
                },
                {
                    "Channel name": "Star Sports 1",
                    "Language": "English",
                    "Embed link": "https://dadocric.st/player.php?id=starsp",
                    "Stream link": "https://dz2.bhalocast.com:7059/hls/str1crows.m3u8?md5=rT3rlHRpWKypYzotwdc9XQ&expires=1774696843&ch=str1crows&s=6bae77a52a1aadf5eea1c81c0b725d57"
                },
                {
                    "Channel name": "Star Sports 2",
                    "Language": "English",
                    "Embed link": "https://dadocric.st/player.php?id=starsp2",
                    "Stream link": "https://dz2.bhalocast.com:7059/hls/str2cows.m3u8?md5=5P3yw9rRtqctJMUNP2Brpw&expires=1774696845&ch=str2cows&s=a15a04beca0da4fb3d724b0d9f24b4b5"
                },
                {
                    "Channel name": "Star Sports Hindi",
                    "Language": "Hindi",
                    "Embed link": "https://dadocric.st/player.php?id=starsp3",
                    "Stream link": "https://dz2.bhalocast.com:7059/hls/str1crowshi.m3u8?md5=2pBtIDOAQ-rmN7tCSoXamA&expires=1774696846&ch=str1crowshi&s=1315b466c2417177aa767f7739b70db7"
                }
            ]
        },
        {
            "Category": "Cricket",
            "Tour/Group name": "IPL T20",
            "match name": "KKR vs MI",
            "Start time": "March 29, 2026, at 2 PM UTC",
            "End time": "March 29, 2026, at 6 PM UTC",
            "Status": "UPCOMING",
            "referer": "https://player0003.com/",
            "User agent": "Mozilla/5.0 (Windows NT 10.0; Win64; x64) AppleWebKit/537.36 (KHTML, like Gecko) Chrome/120.0.0.0 Safari/537.36",
            "Channels": [
                {
                    "Channel name": "Willow Cricket",
                    "Language": "English",
                    "Embed link": "https://dadocric.st/player.php?id=willow",
                    "Stream link": "https://dz2.bhalocast.com:7059/hls/dxdwillo.m3u8?md5=fzdIOlxSJspcUe3koigMtg&expires=1774696849&ch=dxdwillo&s=9fed9905881a7687fcf886650c3e46d0"
                },
                {
                    "Channel name": "Willow Xtra",
                    "Language": "HIndi",
                    "Embed link": "https://dadocric.st/player.php?id=willowextra",
                    "Stream link": "https://dz2.bhalocast.com:7059/hls/dxwillo2.m3u8?md5=LjA14HznjLrKOhS1ZoZTDQ&expires=1774696850&ch=dxwillo2&s=d967c5ad06d381740b6aa4e405e3fa6f"
                },
                {
                    "Channel name": "Star Sports 1",
                    "Language": "English",
                    "Embed link": "https://dadocric.st/player.php?id=starsp",
                    "Stream link": "https://dz2.bhalocast.com:7059/hls/str1crows.m3u8?md5=Q3qwYpOCgmyauB29bsKEoA&expires=1774696851&ch=str1crows&s=e0d12d11a930f386dc88bf42a4338252"
                },
                {
                    "Channel name": "Star Sports 2",
                    "Language": "English",
                    "Embed link": "https://dadocric.st/player.php?id=starsp2",
                    "Stream link": "https://dz2.bhalocast.com:7059/hls/str2cows.m3u8?md5=nhLasQPEOppcKr2UgX1KAQ&expires=1774696853&ch=str2cows&s=cf8b810f43eb57c10f3f5cc6433c8024"
                },
                {
                    "Channel name": "Star Sports Hindi",
                    "Language": "Hindi",
                    "Embed link": "https://dadocric.st/player.php?id=starsp3",
                    "Stream link": "https://dz2.bhalocast.com:7059/hls/str1crowshi.m3u8?md5=-CVtK2KVDmltc-C7XNXPng&expires=1774696854&ch=str1crowshi&s=7841a29f798e476d0d4e3679296f504b"
                }
            ]
        },
        {
            "Category": "Cricket",
            "Tour/Group name": "IPL T20",
            "match name": "CSK vs RR",
            "Start time": "March 30, 2026, at 2 PM UTC",
            "End time": "March 30, 2026, at 6 PM UTC",
            "Status": "UPCOMING",
            "referer": "https://player0003.com/",
            "User agent": "Mozilla/5.0 (Windows NT 10.0; Win64; x64) AppleWebKit/537.36 (KHTML, like Gecko) Chrome/120.0.0.0 Safari/537.36",
            "Channels": [
                {
                    "Channel name": "Willow Cricket",
                    "Language": "English",
                    "Embed link": "https://dadocric.st/player.php?id=willow",
                    "Stream link": "https://dz2.bhalocast.com:7059/hls/dxdwillo.m3u8?md5=RJ_ffW5HQ7JORnQf1_xKrQ&expires=1774696857&ch=dxdwillo&s=9f2b336750db93d4a8aa72d60fae77fa"
                },
                {
                    "Channel name": "Willow Xtra",
                    "Language": "HIndi",
                    "Embed link": "https://dadocric.st/player.php?id=willowextra",
                    "Stream link": "https://dz2.bhalocast.com:7059/hls/dxwillo2.m3u8?md5=tat53wMImhjfl_J6DpP7Cw&expires=1774696858&ch=dxwillo2&s=02f62df9a3d83367fffd411dfb953460"
                },
                {
                    "Channel name": "Star Sports 1",
                    "Language": "English",
                    "Embed link": "https://dadocric.st/player.php?id=starsp",
                    "Stream link": "https://dz2.bhalocast.com:7059/hls/str1crows.m3u8?md5=GW1V3aDTVyhFKv_Ux_YB0g&expires=1774696860&ch=str1crows&s=25a8f2f29e360efb63d162eea80960fc"
                },
                {
                    "Channel name": "Star Sports 2",
                    "Language": "English",
                    "Embed link": "https://dadocric.st/player.php?id=starsp2",
                    "Stream link": "https://dz2.bhalocast.com:7059/hls/str2cows.m3u8?md5=XX-d5vH0VxLIjqlIpAxp3w&expires=1774696861&ch=str2cows&s=8a1ff18b52d5eab95bb90ae54ff79e32"
                },
                {
                    "Channel name": "Star Sports Hindi",
                    "Language": "Hindi",
                    "Embed link": "https://dadocric.st/player.php?id=starsp3",
                    "Stream link": "https://dz2.bhalocast.com:7059/hls/str1crowshi.m3u8?md5=LlF_YYBZH--55Ugsm_XdXg&expires=1774696863&ch=str1crowshi&s=2c51683d86a20cca1c5ea929d3fc4f21"
                }
            ]
        }
    ]
}